synapse_ai/__init__.py
synapse_ai/eda.py
synapse_ai/mel_spectrograms.py
synapse_ai/phonemes.py
synapse_ai/DNN/__init__.py
synapse_ai/DNN/model_configurator.py
synapse_ai/DNN/src/Logo.ico
synapse_ai/DNN/src/Logo.png
synapse_ai/DNN/src/tf.png
synapse_ai_tools-0.3.2.dist-info/licenses/LICENSE
synapse_ai_tools-0.3.2.dist-info/METADATA
synapse_ai_tools-0.3.2.dist-info/WHEEL
synapse_ai_tools-0.3.2.dist-info/top_level.txt
synapse_ai_tools-0.3.2.dist-info/RECORD
