Metadata-Version: 2.4
Name: synapse_ai_tools
Version: 0.3.2
Summary: A Python package for artificial intelligence development, providing utilities for machine learning, deep learning, data processing, and model deployment.
Author: SYNAPSE AI SAS
Author-email: servicios@groupsynapseai.com
Classifier: Programming Language :: Python :: 3
Classifier: License :: OSI Approved :: MIT License
Classifier: Operating System :: OS Independent
Requires-Python: >=3.6, <3.11
License-File: LICENSE
Requires-Dist: matplotlib
Requires-Dist: seaborn
Requires-Dist: pandas
Requires-Dist: numpy<2.0
Requires-Dist: librosa
Requires-Dist: pydot
Requires-Dist: tensorflow==2.10
Requires-Dist: scikit-learn
Requires-Dist: pillow
Dynamic: author
Dynamic: author-email
Dynamic: classifier
Dynamic: description
Dynamic: description-content-type
Dynamic: license-file
Dynamic: requires-dist
Dynamic: requires-python
Dynamic: summary
